{"trial_id": "464d16860a611464429ccc03673810a8", "hyperparameters": {"space": [{"class_name": "Float", "config": {"name": "learning_rate", "default": 0.005, "conditions": [], "min_value": 0.005, "max_value": 0.5, "step": null, "sampling": "log"}}, {"class_name": "Choice", "config": {"name": "regularization", "default": "l1", "conditions": [], "values": ["l1", "l2", "elasticinet", "None"], "ordered": false}}, {"class_name": "Float", "config": {"name": "l1", "default": 0.0005, "conditions": [{"class_name": "Parent", "config": {"name": "regularization", "values": ["l1", "elasticinet"]}}], "min_value": 0.0005, "max_value": 0.5, "step": null, "sampling": "log"}}, {"class_name": "Float", "config": {"name": "l2", "default": 0.0005, "conditions": [{"class_name": "Parent", "config": {"name": "regularization", "values": ["l2", "elasticinet"]}}], "min_value": 0.0005, "max_value": 0.5, "step": null, "sampling": "log"}}], "values": {"learning_rate": 0.030600529016649523, "regularization": "None"}}, "metrics": {"metrics": {"loss": {"direction": "min", "observations": [{"value": [0.004105982603505254], "step": 0}]}, "mse": {"direction": "min", "observations": [{"value": [0.004105982603505254], "step": 0}]}, "val_loss": {"direction": "min", "observations": [{"value": [0.005133332684636116], "step": 0}]}, "val_mse": {"direction": "min", "observations": [{"value": [0.005133332529415687], "step": 0}]}}}, "score": 0.004105982603505254, "best_step": 0, "status": "COMPLETED"}